sams/__init__.py
sams/base.py
sams/core.py
sams/aggregator/SoftwareAccounting.py
sams/aggregator/SoftwareAccountingPW.py
sams/aggregator/__init__.py
sams/backend/SoftwareAccounting.py
sams/backend/SoftwareAccountingPW.py
sams/backend/__init__.py
sams/listener/Prometheus.py
sams/listener/__init__.py
sams/loader/File.py
sams/loader/FileSlurmInfoFallback.py
sams/loader/__init__.py
sams/output/Carbon.py
sams/output/Collectd.py
sams/output/File.py
sams/output/Http.py
sams/output/Prometheus.py
sams/output/__init__.py
sams/pidfinder/Slurm.py
sams/pidfinder/__init__.py
sams/sampler/Core.py
sams/sampler/FSStats.py
sams/sampler/IOStats.py
sams/sampler/NvidiaSMI.py
sams/sampler/Pressure.py
sams/sampler/SlurmCGroup.py
sams/sampler/SlurmCGroup2.py
sams/sampler/SlurmInfo.py
sams/sampler/Software.py
sams/sampler/ZFSStats.py
sams/sampler/__init__.py
sams/software/Regexp.py
sams/software/__init__.py
sams/xmlwriter/File.py
sams/xmlwriter/__init__.py
softwareaccounting-1.9a4.data/scripts/sams-aggregator.py
softwareaccounting-1.9a4.data/scripts/sams-collector.py
softwareaccounting-1.9a4.data/scripts/sams-post-receiver.py
softwareaccounting-1.9a4.data/scripts/sams-software-extractor.py
softwareaccounting-1.9a4.data/scripts/sams-software-updater.py
softwareaccounting-1.9a4.data/scripts/sgas-sa-registrant
softwareaccounting-1.9a4.dist-info/LICENSE
softwareaccounting-1.9a4.dist-info/METADATA
softwareaccounting-1.9a4.dist-info/WHEEL
softwareaccounting-1.9a4.dist-info/top_level.txt
softwareaccounting-1.9a4.dist-info/RECORD
